[
    {
        "blocks": 57,
        "by": "sapo",
        "comments": 127,
        "hn_url": "https://news.ycombinator.com/item?id=26860925",
        "item_id": 26860925,
        "ratio": 1.1441441441441442,
        "score": 111,
        "submission_time": "2021-04-19T18:01:15",
        "title": "Test for lists in Cython",
        "url": "https://github.com/00sapo/cython_list_test"
    },
    {
        "blocks": 56,
        "by": "prostoalex",
        "comments": 54,
        "hn_url": "https://news.ycombinator.com/item?id=26863482",
        "item_id": 26863482,
        "ratio": 1.125,
        "score": 48,
        "submission_time": "2021-04-19T23:02:28",
        "title": "SmartFarm device to harvest air moisture for self-sustaining urban farming",
        "url": "https://news.nus.edu.sg/smartfarm-harvest-air-moisture-for-urban-farming/"
    },
    {
        "blocks": 53,
        "by": "tyho",
        "comments": 207,
        "hn_url": "https://news.ycombinator.com/item?id=26860763",
        "item_id": 26860763,
        "ratio": 1.078125,
        "score": 192,
        "submission_time": "2021-04-19T17:36:40",
        "title": "Bank of England to explore a potential Central Bank Digital Currency",
        "url": "https://www.bankofengland.co.uk/news/2021/april/bank-of-england-statement-on-central-bank-digital-currency"
    },
    {
        "blocks": 46,
        "by": "jfmengels1",
        "comments": 96,
        "hn_url": "https://news.ycombinator.com/item?id=26860919",
        "item_id": 26860919,
        "ratio": 0.9320388349514563,
        "score": 103,
        "submission_time": "2021-04-19T18:00:23",
        "title": "Why we chose Elm for Humio\u2019s web UI",
        "url": "https://www.humio.com/whats-new/blog/why-we-chose-elm-for-humio-s-web-ui"
    },
    {
        "blocks": 42,
        "by": "ftruzzi",
        "comments": 323,
        "hn_url": "https://news.ycombinator.com/item?id=26863052",
        "item_id": 26863052,
        "ratio": 0.847769028871391,
        "score": 381,
        "submission_time": "2021-04-19T22:23:44",
        "title": "Hire me and pay what you want, just give me interesting work",
        "url": "https://truzzi.me/hire-me-pay-what-you-want-interesting-work/"
    },
    {
        "blocks": 39,
        "by": "jgrimm",
        "comments": 96,
        "hn_url": "https://news.ycombinator.com/item?id=26862318",
        "item_id": 26862318,
        "ratio": 0.7933884297520661,
        "score": 121,
        "submission_time": "2021-04-19T21:07:59",
        "title": "Proposal: expression to create pointer to simple types",
        "url": "https://github.com/golang/go/issues/45624"
    },
    {
        "blocks": 38,
        "by": "isomorph",
        "comments": 92,
        "hn_url": "https://news.ycombinator.com/item?id=26863490",
        "item_id": 26863490,
        "ratio": 0.7666666666666667,
        "score": 120,
        "submission_time": "2021-04-19T23:03:23",
        "title": "The Terrifyingly Prescient \u2018Serial Experiments Lain,\u2019 20 Years Later (2018)",
        "url": "https://www.theringer.com/tv/2018/7/9/17544220/serial-experiments-lain-anime-20-years"
    },
    {
        "blocks": 38,
        "by": "daverol",
        "comments": 16,
        "hn_url": "https://news.ycombinator.com/item?id=26860643",
        "item_id": 26860643,
        "ratio": 0.7619047619047619,
        "score": 21,
        "submission_time": "2021-04-19T17:18:49",
        "title": "Product placements may be added to classic films",
        "url": "https://www.bbc.co.uk/news/business-56758376"
    },
    {
        "blocks": 37,
        "by": "manx",
        "comments": 89,
        "hn_url": "https://news.ycombinator.com/item?id=26860992",
        "item_id": 26860992,
        "ratio": 0.7478991596638656,
        "score": 119,
        "submission_time": "2021-04-19T18:10:26",
        "title": "Start a Business from Plastic Waste",
        "url": "http://preciousplastic.com/"
    },
    {
        "blocks": 32,
        "by": "the_arun",
        "comments": 74,
        "hn_url": "https://news.ycombinator.com/item?id=26859058",
        "item_id": 26859058,
        "ratio": 0.6434782608695652,
        "score": 115,
        "submission_time": "2021-04-19T12:18:40",
        "title": "DIY Camera Using Raspberry Pi",
        "url": "https://ruha.camera/"
    },
    {
        "blocks": 30,
        "by": "easton",
        "comments": 164,
        "hn_url": "https://news.ycombinator.com/item?id=26864009",
        "item_id": 26864009,
        "ratio": 0.6188679245283019,
        "score": 265,
        "submission_time": "2021-04-19T23:41:46",
        "title": "Firefox 88.0",
        "url": "https://www.mozilla.org/en-US/firefox/88.0/releasenotes/"
    },
    {
        "blocks": 28,
        "by": "rdpintqogeogsaa",
        "comments": 87,
        "hn_url": "https://news.ycombinator.com/item?id=26866482",
        "item_id": 26866482,
        "ratio": 0.58,
        "score": 150,
        "submission_time": "2021-04-20T02:44:49",
        "title": "A List of Hacker News's Undocumented Features and Behaviors (2018-20)",
        "url": "https://github.com/minimaxir/hacker-news-undocumented"
    },
    {
        "blocks": 28,
        "by": "rdpintqogeogsaa",
        "comments": 26,
        "hn_url": "https://news.ycombinator.com/item?id=26866065",
        "item_id": 26866065,
        "ratio": 0.5652173913043478,
        "score": 46,
        "submission_time": "2021-04-20T02:06:16",
        "title": "J2 open processor: an open source processor using the SuperH ISA",
        "url": "https://j-core.org/"
    },
    {
        "blocks": 27,
        "by": "panic",
        "comments": 188,
        "hn_url": "https://news.ycombinator.com/item?id=26863172",
        "item_id": 26863172,
        "ratio": 0.5481049562682215,
        "score": 343,
        "submission_time": "2021-04-19T22:33:57",
        "title": "Facebook gives money to America\u2019s biggest news organizations",
        "url": "https://washingtonmonthly.com/2021/04/19/is-facebook-buying-off-the-new-york-times/"
    },
    {
        "blocks": 26,
        "by": "Tomte",
        "comments": 285,
        "hn_url": "https://news.ycombinator.com/item?id=26863907",
        "item_id": 26863907,
        "ratio": 0.5268022181146026,
        "score": 541,
        "submission_time": "2021-04-19T23:33:48",
        "title": "Microsoft says mandatory password changing is \u201cancient and obsolete\u201d (2019)",
        "url": "https://arstechnica.com/information-technology/2019/06/microsoft-says-mandatory-password-changing-is-ancient-and-obsolete/"
    },
    {
        "blocks": 24,
        "by": "marc__1",
        "comments": 167,
        "hn_url": "https://news.ycombinator.com/item?id=26861843",
        "item_id": 26861843,
        "ratio": 0.48546511627906974,
        "score": 344,
        "submission_time": "2021-04-19T20:10:14",
        "title": "Proposed acquisition of ARM Limited by NVIDIA: public interest intervention",
        "url": "https://www.gov.uk/government/publications/proposed-acquisition-of-arm-limited-by-nvidia-corporation-public-interest-intervention"
    },
    {
        "blocks": 24,
        "by": "Tomte",
        "comments": 30,
        "hn_url": "https://news.ycombinator.com/item?id=26867300",
        "item_id": 26867300,
        "ratio": 0.4838709677419355,
        "score": 62,
        "submission_time": "2021-04-20T04:01:04",
        "title": "The \u201cGranny Knot\u201d",
        "url": "https://www.fieggen.com/shoelace/grannyknot.htm"
    },
    {
        "blocks": 23,
        "by": "kumarharsh",
        "comments": 37,
        "hn_url": "https://news.ycombinator.com/item?id=26864264",
        "item_id": 26864264,
        "ratio": 0.4625,
        "score": 80,
        "submission_time": "2021-04-20T00:01:29",
        "title": "Huawei \u2018may have eavesdropped on Dutch mobile network\u2019s calls\u2019",
        "url": "https://www.theguardian.com/technology/2021/apr/19/huawei-may-have-eavesdropped-on-dutch-mobile-networks-calls"
    },
    {
        "blocks": 22,
        "by": "pcdoodle",
        "comments": 189,
        "hn_url": "https://news.ycombinator.com/item?id=26860609",
        "item_id": 26860609,
        "ratio": 0.4587378640776699,
        "score": 412,
        "submission_time": "2021-04-19T17:14:19",
        "title": "Thinkpad X230 with \u201ce-Ink\u201d display at 30fps [video]",
        "url": "https://www.youtube.com/watch?v=HuegrU_kIq8"
    },
    {
        "blocks": 21,
        "by": "weinzierl",
        "comments": 158,
        "hn_url": "https://news.ycombinator.com/item?id=26860150",
        "item_id": 26860150,
        "ratio": 0.42934782608695654,
        "score": 368,
        "submission_time": "2021-04-19T16:02:58",
        "title": "Large-Scale Abuse of Contact Discovery in Mobile Messengers [pdf]",
        "url": "https://www.ndss-symposium.org/wp-content/uploads/ndss2021_1C-3_23159_paper.pdf"
    },
    {
        "blocks": 19,
        "by": "mvanga",
        "comments": 149,
        "hn_url": "https://news.ycombinator.com/item?id=26859907",
        "item_id": 26859907,
        "ratio": 0.3900523560209424,
        "score": 382,
        "submission_time": "2021-04-19T15:18:29",
        "title": "Basic Music Theory in ~200 Lines of Python",
        "url": "https://www.mvanga.com/blog/basic-music-theory-in-200-lines-of-python"
    },
    {
        "blocks": 17,
        "by": "geerlingguy",
        "comments": 67,
        "hn_url": "https://news.ycombinator.com/item?id=26858614",
        "item_id": 26858614,
        "ratio": 0.3471502590673575,
        "score": 193,
        "submission_time": "2021-04-19T10:28:29",
        "title": "MirkoPC \u2013 a Raspberry Pi CM4-powered computer made in Poland",
        "url": "https://www.jeffgeerling.com/blog/2021/mirkopc-full-featured-raspberry-pi-desktop-computer"
    },
    {
        "blocks": 17,
        "by": "ttflee",
        "comments": 58,
        "hn_url": "https://news.ycombinator.com/item?id=26860435",
        "item_id": 26860435,
        "ratio": 0.3411764705882353,
        "score": 170,
        "submission_time": "2021-04-19T16:54:12",
        "title": "This is what Doom looks like on a holographic display",
        "url": "https://twitter.com/jankais3r/status/1383865733063479304"
    },
    {
        "blocks": 16,
        "by": "franky47",
        "comments": 37,
        "hn_url": "https://news.ycombinator.com/item?id=26861728",
        "item_id": 26861728,
        "ratio": 0.3333333333333333,
        "score": 111,
        "submission_time": "2021-04-19T19:54:41",
        "title": "Representing SHA-256 Hashes as Avatars",
        "url": "https://francoisbest.com/posts/2021/hashvatars?demo=Hello,%20Hacker%20News%21"
    },
    {
        "blocks": 16,
        "by": "milliams",
        "comments": 37,
        "hn_url": "https://news.ycombinator.com/item?id=26861875",
        "item_id": 26861875,
        "ratio": 0.33035714285714285,
        "score": 112,
        "submission_time": "2021-04-19T20:15:22",
        "title": "What's in the Box?",
        "url": "https://fasterthanli.me/articles/whats-in-the-box"
    },
    {
        "blocks": 16,
        "by": "harperlee",
        "comments": 63,
        "hn_url": "https://news.ycombinator.com/item?id=26860627",
        "item_id": 26860627,
        "ratio": 0.3298429319371728,
        "score": 191,
        "submission_time": "2021-04-19T17:16:49",
        "title": "Deriving the piano keyboard from biological principles using clustering",
        "url": "https://fiftysevendegreesofrad.github.io/JupyterNotes/piano.html"
    },
    {
        "blocks": 16,
        "by": "todsacerdoti",
        "comments": 19,
        "hn_url": "https://news.ycombinator.com/item?id=26864213",
        "item_id": 26864213,
        "ratio": 0.3220338983050847,
        "score": 59,
        "submission_time": "2021-04-19T23:56:58",
        "title": "PiDP-11 \u2013 Recreating PDP-11/70 with Raspberry Pi",
        "url": "https://retroviator.com/2020/03/01/pidp-11/"
    },
    {
        "blocks": 15,
        "by": "deeyago",
        "comments": 85,
        "hn_url": "https://news.ycombinator.com/item?id=26858741",
        "item_id": 26858741,
        "ratio": 0.31365313653136534,
        "score": 271,
        "submission_time": "2021-04-19T11:02:13",
        "title": "Open source \u201csplit-flap\u201d mechanical display",
        "url": "https://github.com/scottbez1/splitflap"
    },
    {
        "blocks": 14,
        "by": "tndl",
        "comments": 49,
        "hn_url": "https://news.ycombinator.com/item?id=26858935",
        "item_id": 26858935,
        "ratio": 0.28488372093023256,
        "score": 172,
        "submission_time": "2021-04-19T11:40:19",
        "title": "Job board to work on problems like climate change and food insecurity",
        "url": "https://goodjobs.careers/"
    },
    {
        "blocks": 13,
        "by": "moklick",
        "comments": 47,
        "hn_url": "https://news.ycombinator.com/item?id=26860381",
        "item_id": 26860381,
        "ratio": 0.27325581395348836,
        "score": 172,
        "submission_time": "2021-04-19T16:46:22",
        "title": "Show HN: React Flow \u2013 library for creating node based editors and apps",
        "url": "https://github.com/wbkd/react-flow"
    },
    {
        "blocks": 13,
        "by": "samclemens",
        "comments": 14,
        "hn_url": "https://news.ycombinator.com/item?id=26854896",
        "item_id": 26854896,
        "ratio": 0.2641509433962264,
        "score": 53,
        "submission_time": "2021-04-19T02:18:04",
        "title": "Jumping Frenchmen of Maine",
        "url": "https://en.wikipedia.org/wiki/Jumping_Frenchmen_of_Maine"
    },
    {
        "blocks": 12,
        "by": "ca98am79",
        "comments": 46,
        "hn_url": "https://news.ycombinator.com/item?id=26865832",
        "item_id": 26865832,
        "ratio": 0.25555555555555554,
        "score": 180,
        "submission_time": "2021-04-20T01:48:34",
        "title": "Zenreader: A 4.7 Inches E-Ink RSS Reader Powered by ESP32",
        "url": "https://www.tnhh.net/posts/zenreader-4.7-in-rss-eink-reader.html"
    },
    {
        "blocks": 12,
        "by": "pcr910303",
        "comments": 50,
        "hn_url": "https://news.ycombinator.com/item?id=26858635",
        "item_id": 26858635,
        "ratio": 0.25125628140703515,
        "score": 199,
        "submission_time": "2021-04-19T10:34:32",
        "title": "ArchiveBox: Open-source self-hosted web archiving",
        "url": "https://archivebox.io/"
    },
    {
        "blocks": 11,
        "by": "marcodiego",
        "comments": 114,
        "hn_url": "https://news.ycombinator.com/item?id=26858053",
        "item_id": 26858053,
        "ratio": 0.23505154639175257,
        "score": 485,
        "submission_time": "2021-04-19T08:42:28",
        "title": "Dissecting the Apple M1 GPU, Part III",
        "url": "https://rosenzweig.io/blog/asahi-gpu-part-3.html"
    },
    {
        "blocks": 11,
        "by": "feross",
        "comments": 11,
        "hn_url": "https://news.ycombinator.com/item?id=26867465",
        "item_id": 26867465,
        "ratio": 0.23404255319148937,
        "score": 47,
        "submission_time": "2021-04-20T04:16:37",
        "title": "Everyone Loves the $100M Deli",
        "url": "https://www.bloomberg.com/opinion/articles/2021-04-19/everyone-loves-the-100-million-new-jersey-deli-except-david-einhorn-knottrmb"
    },
    {
        "blocks": 10,
        "by": "hheikinh",
        "comments": 105,
        "hn_url": "https://news.ycombinator.com/item?id=26860842",
        "item_id": 26860842,
        "ratio": 0.21694214876033058,
        "score": 484,
        "submission_time": "2021-04-19T17:47:21",
        "title": "First Flight of the Ingenuity Mars Helicopter [video]",
        "url": "https://www.youtube.com/watch?v=p1KolyCqICI"
    },
    {
        "blocks": 8,
        "by": "runpat",
        "comments": 42,
        "hn_url": "https://news.ycombinator.com/item?id=26859895",
        "item_id": 26859895,
        "ratio": 0.1721311475409836,
        "score": 244,
        "submission_time": "2021-04-19T15:16:39",
        "title": "Bitcoin Blockchain Visualization",
        "url": "https://symphony.iohk.io/en/"
    },
    {
        "blocks": 2,
        "by": "xeeeeeeeeeeenu",
        "comments": 1,
        "hn_url": "https://news.ycombinator.com/item?id=26860062",
        "item_id": 26860062,
        "ratio": 0.047619047619047616,
        "score": 21,
        "submission_time": "2021-04-19T15:45:31",
        "title": "IPTIA Fidonet/Usenet Message Archive",
        "url": "http://www.ipingthereforeiam.com/bbs/msgs/"
    }
]