[
    {
        "blocks": 103,
        "by": "jakecopp",
        "comments": 169,
        "hn_url": "https://news.ycombinator.com/item?id=34058004",
        "item_id": 34058004,
        "ratio": 2.0609756097560976,
        "score": 82,
        "submission_time": "2022-12-19T21:29:55",
        "title": "Sydney CBD is bringing back pedestrian \u201cbeg buttons\u201d",
        "url": "https://jakecoppinger.com/2022/12/sydney-cbd-is-bringing-back-pedestrian-beg-buttons/"
    },
    {
        "blocks": 88,
        "by": "ryzvonusef",
        "comments": 866,
        "hn_url": "https://news.ycombinator.com/item?id=34039816",
        "item_id": 34039816,
        "ratio": 1.7637474541751528,
        "score": 491,
        "submission_time": "2022-12-18T17:17:54",
        "title": "Stanford's \u201cElimination of Harmful Language\u201d Initiative",
        "url": "https://itcommunity.stanford.edu/ehli"
    },
    {
        "blocks": 78,
        "by": "fbn79",
        "comments": 400,
        "hn_url": "https://news.ycombinator.com/item?id=34057671",
        "item_id": 34057671,
        "ratio": 1.5686274509803921,
        "score": 255,
        "submission_time": "2022-12-19T21:02:55",
        "title": "What happened to the first cryogenically frozen humans?",
        "url": "https://bigthink.com/the-future/cryonics-horror-stories/"
    },
    {
        "blocks": 62,
        "by": "mfiguiere",
        "comments": 233,
        "hn_url": "https://news.ycombinator.com/item?id=34059633",
        "item_id": 34059633,
        "ratio": 1.2594594594594595,
        "score": 185,
        "submission_time": "2022-12-19T23:59:22",
        "title": "Amazon Ring cameras used in nationwide \u2018swatting\u2019 spree, US Justice Dept. says",
        "url": "https://www.bloomberg.com/news/articles/2022-12-19/two-charged-with-using-amazon-ring-cameras-in-nationwide-swatting-spree"
    },
    {
        "blocks": 51,
        "by": "MoSattler",
        "comments": 58,
        "hn_url": "https://news.ycombinator.com/item?id=34063952",
        "item_id": 34063952,
        "ratio": 1.0357142857142858,
        "score": 56,
        "submission_time": "2022-12-20T10:21:02",
        "title": "Elon Musk\u2019s $44B education on free speech",
        "url": "https://www.economist.com/leaders/2022/12/19/elon-musks-44bn-education-on-free-speech"
    },
    {
        "blocks": 50,
        "by": "pulse7",
        "comments": 55,
        "hn_url": "https://news.ycombinator.com/item?id=34063460",
        "item_id": 34063460,
        "ratio": 1.0,
        "score": 55,
        "submission_time": "2022-12-20T09:06:39",
        "title": "Apple Is Struggling to Build Mac Pro Based on Its Own Silicon",
        "url": "https://www.tomshardware.com/news/apple-struggles-to-build-mac-pro-based-on-own-cpus"
    },
    {
        "blocks": 35,
        "by": "drdee",
        "comments": 163,
        "hn_url": "https://news.ycombinator.com/item?id=34043118",
        "item_id": 34043118,
        "ratio": 0.7149122807017544,
        "score": 228,
        "submission_time": "2022-12-18T20:47:15",
        "title": "\u2018Perpetual broths\u2019 that simmer for decades",
        "url": "https://www.atlasobscura.com/articles/perpetual-broth"
    },
    {
        "blocks": 34,
        "by": "masenf",
        "comments": 73,
        "hn_url": "https://news.ycombinator.com/item?id=34061252",
        "item_id": 34061252,
        "ratio": 0.6822429906542056,
        "score": 107,
        "submission_time": "2022-12-20T03:41:21",
        "title": "Boring Python: Code quality",
        "url": "https://www.b-list.org/weblog/2022/dec/19/boring-python-code-quality/"
    },
    {
        "blocks": 30,
        "by": "matt_d",
        "comments": 70,
        "hn_url": "https://news.ycombinator.com/item?id=34058421",
        "item_id": 34058421,
        "ratio": 0.6194690265486725,
        "score": 113,
        "submission_time": "2022-12-19T22:07:45",
        "title": "Fast memcpy, a system design",
        "url": "https://www.sigarch.org/fast-memcpy-a-system-design/"
    },
    {
        "blocks": 30,
        "by": "redbell",
        "comments": 109,
        "hn_url": "https://news.ycombinator.com/item?id=34060219",
        "item_id": 34060219,
        "ratio": 0.6123595505617978,
        "score": 178,
        "submission_time": "2022-12-20T01:08:02",
        "title": "The Windows Subsystem for Android now runs Android 13 in beta",
        "url": "https://github.com/microsoft/WSA/discussions/167"
    },
    {
        "blocks": 28,
        "by": "fagnerbrack",
        "comments": 81,
        "hn_url": "https://news.ycombinator.com/item?id=34061206",
        "item_id": 34061206,
        "ratio": 0.574468085106383,
        "score": 141,
        "submission_time": "2022-12-20T03:32:58",
        "title": "\u201cLaws\u201d of software estimation for complex work (2021)",
        "url": "https://mdalmijn.com/p/11-laws-of-software-estimation-for-complex-work"
    },
    {
        "blocks": 28,
        "by": "DamnInteresting",
        "comments": 132,
        "hn_url": "https://news.ycombinator.com/item?id=34057699",
        "item_id": 34057699,
        "ratio": 0.5617021276595745,
        "score": 235,
        "submission_time": "2022-12-19T21:04:59",
        "title": "How did Roomba-recorded photos end up on Facebook?",
        "url": "https://www.technologyreview.com/2022/12/19/1065306/roomba-irobot-robot-vacuums-artificial-intelligence-training-data-privacy/"
    },
    {
        "blocks": 26,
        "by": "danparsonson",
        "comments": 26,
        "hn_url": "https://news.ycombinator.com/item?id=34062802",
        "item_id": 34062802,
        "ratio": 0.5306122448979592,
        "score": 49,
        "submission_time": "2022-12-20T07:39:15",
        "title": "Ask HN: What Happened to Pinboard (Dec '22 edition)?",
        "url": null
    },
    {
        "blocks": 25,
        "by": "bmalicoat",
        "comments": 18,
        "hn_url": "https://news.ycombinator.com/item?id=34058358",
        "item_id": 34058358,
        "ratio": 0.5142857142857142,
        "score": 35,
        "submission_time": "2022-12-19T22:00:06",
        "title": "Show HN: Yahtzee and Poker and Cosmic Horror = Pine Tar Poker",
        "url": "https://www.pinetarpoker.com"
    },
    {
        "blocks": 24,
        "by": "tosh",
        "comments": 39,
        "hn_url": "https://news.ycombinator.com/item?id=34059744",
        "item_id": 34059744,
        "ratio": 0.4875,
        "score": 80,
        "submission_time": "2022-12-20T00:11:30",
        "title": "FILM: Frame Interpolation for Large Motion",
        "url": "https://github.com/google-research/frame-interpolation"
    },
    {
        "blocks": 23,
        "by": "kalimanzaro",
        "comments": 130,
        "hn_url": "https://news.ycombinator.com/item?id=34051868",
        "item_id": 34051868,
        "ratio": 0.4642857142857143,
        "score": 280,
        "submission_time": "2022-12-19T13:39:34",
        "title": "Evidence that the evolution of mammals began in the Southern Hemisphere",
        "url": "https://www.australiangeographic.com.au/news/2022/12/discovery-identifies-australia-as-birthplace-of-all-modern-mammals/"
    },
    {
        "blocks": 22,
        "by": "dananjaya86",
        "comments": 38,
        "hn_url": "https://news.ycombinator.com/item?id=34063290",
        "item_id": 34063290,
        "ratio": 0.4470588235294118,
        "score": 85,
        "submission_time": "2022-12-20T08:46:01",
        "title": "The Knights Templar started London's first bank (2017)",
        "url": "https://www.bbc.com/news/business-38499883"
    },
    {
        "blocks": 22,
        "by": "shaman1",
        "comments": 15,
        "hn_url": "https://news.ycombinator.com/item?id=34064191",
        "item_id": 34064191,
        "ratio": 0.4411764705882353,
        "score": 34,
        "submission_time": "2022-12-20T10:52:05",
        "title": "UK bank fined \u00a349M over IT system meltdown",
        "url": "https://www.bbc.com/news/business-64036529"
    },
    {
        "blocks": 20,
        "by": "vmatsiiako",
        "comments": 90,
        "hn_url": "https://news.ycombinator.com/item?id=34055132",
        "item_id": 34055132,
        "ratio": 0.4147465437788018,
        "score": 217,
        "submission_time": "2022-12-19T17:52:20",
        "title": "Show HN: Infisical \u2013 open-source secrets manager",
        "url": "https://github.com/Infisical/infisical"
    },
    {
        "blocks": 19,
        "by": "ibobev",
        "comments": 26,
        "hn_url": "https://news.ycombinator.com/item?id=34063720",
        "item_id": 34063720,
        "ratio": 0.3880597014925373,
        "score": 67,
        "submission_time": "2022-12-20T09:41:44",
        "title": "Amiga Forever",
        "url": "https://www.amigaforever.com"
    },
    {
        "blocks": 19,
        "by": "sails",
        "comments": 18,
        "hn_url": "https://news.ycombinator.com/item?id=34036978",
        "item_id": 34036978,
        "ratio": 0.3829787234042553,
        "score": 47,
        "submission_time": "2022-12-18T12:12:55",
        "title": "Why Can\u2019t We Get a Handle on This Safety Thing? (1998)",
        "url": "https://www.ushpa.org/page/why-can-t-we-get-a-handle-on-this-safety-thing"
    },
    {
        "blocks": 18,
        "by": "mmastrac",
        "comments": 103,
        "hn_url": "https://news.ycombinator.com/item?id=34043314",
        "item_id": 34043314,
        "ratio": 0.3772893772893773,
        "score": 273,
        "submission_time": "2022-12-18T21:01:53",
        "title": "EABitTricks.h",
        "url": "https://github.com/electronicarts/EAStdC/blob/master/include/EAStdC/EABitTricks.h"
    },
    {
        "blocks": 18,
        "by": "ibobev",
        "comments": 36,
        "hn_url": "https://news.ycombinator.com/item?id=34058856",
        "item_id": 34058856,
        "ratio": 0.3711340206185567,
        "score": 97,
        "submission_time": "2022-12-19T22:44:36",
        "title": "Implementing \u2018strlen\u2019 using SVE",
        "url": "https://lemire.me/blog/2022/12/19/implementing-strlen-using-sve/"
    },
    {
        "blocks": 18,
        "by": "indus",
        "comments": 18,
        "hn_url": "https://news.ycombinator.com/item?id=34025981",
        "item_id": 34025981,
        "ratio": 0.3673469387755102,
        "score": 49,
        "submission_time": "2022-12-17T08:35:23",
        "title": "Rarest clouds in the world appear over the SF Bay Area",
        "url": "https://www.sfgate.com/bayarea/article/Rare-noctilucent-clouds-appear-in-SF-Bay-Area-17659007.php"
    },
    {
        "blocks": 16,
        "by": "brudgers",
        "comments": 99,
        "hn_url": "https://news.ycombinator.com/item?id=34054718",
        "item_id": 34054718,
        "ratio": 0.3311036789297659,
        "score": 299,
        "submission_time": "2022-12-19T17:22:07",
        "title": "Cook whole grains like popcorn (2018)",
        "url": "https://www.treehugger.com/how-cook-any-whole-grain-popcorn-4858738"
    },
    {
        "blocks": 16,
        "by": "zdw",
        "comments": 45,
        "hn_url": "https://news.ycombinator.com/item?id=34061511",
        "item_id": 34061511,
        "ratio": 0.3284671532846715,
        "score": 137,
        "submission_time": "2022-12-20T04:23:25",
        "title": "Towards a More Open Secure Element Chip",
        "url": "https://www.bunniestudios.com/blog/?p=6606"
    },
    {
        "blocks": 14,
        "by": "fahrradflucht",
        "comments": 181,
        "hn_url": "https://news.ycombinator.com/item?id=34056067",
        "item_id": 34056067,
        "ratio": 0.2928802588996764,
        "score": 618,
        "submission_time": "2022-12-19T18:56:38",
        "title": "Spotifyd",
        "url": "https://github.com/Spotifyd/spotifyd"
    },
    {
        "blocks": 13,
        "by": "vincentchau",
        "comments": 44,
        "hn_url": "https://news.ycombinator.com/item?id=34061110",
        "item_id": 34061110,
        "ratio": 0.2732919254658385,
        "score": 161,
        "submission_time": "2022-12-20T03:15:30",
        "title": "Valve is paying open source developers to keep Steam Deck playable",
        "url": "https://www.pcgamer.com/valve-is-paying-a-whole-lot-of-developers-to-keep-the-steam-decks-open-source-software-going/"
    },
    {
        "blocks": 11,
        "by": "JohnHendrix",
        "comments": 147,
        "hn_url": "https://news.ycombinator.com/item?id=34029045",
        "item_id": 34029045,
        "ratio": 0.23863636363636365,
        "score": 616,
        "submission_time": "2022-12-17T16:14:44",
        "title": "Productivity Blocker",
        "url": "https://www.productivityblocker.com"
    },
    {
        "blocks": 9,
        "by": "varjag",
        "comments": 32,
        "hn_url": "https://news.ycombinator.com/item?id=34058658",
        "item_id": 34058658,
        "ratio": 0.18823529411764706,
        "score": 170,
        "submission_time": "2022-12-19T22:27:53",
        "title": "Astronomical Calculations for Hard SF in Common Lisp",
        "url": "https://borretti.me/article/astronomical-calculations-for-hard-sf-common-lisp"
    },
    {
        "blocks": 9,
        "by": "solene",
        "comments": 34,
        "hn_url": "https://news.ycombinator.com/item?id=34055533",
        "item_id": 34055533,
        "ratio": 0.18579234972677597,
        "score": 183,
        "submission_time": "2022-12-19T18:19:08",
        "title": "GCC now includes Modula-2 and Rust. Do they work on OpenBSD?",
        "url": "https://briancallahan.net/blog/20221219.html"
    },
    {
        "blocks": 8,
        "by": "ibobev",
        "comments": 19,
        "hn_url": "https://news.ycombinator.com/item?id=34050351",
        "item_id": 34050351,
        "ratio": 0.168141592920354,
        "score": 113,
        "submission_time": "2022-12-19T10:00:25",
        "title": "How to draw ugly lines fast",
        "url": "https://cohost.org/tomforsyth/post/648716-how-to-draw-ugly-lin"
    },
    {
        "blocks": 8,
        "by": "jerryjerryjerry",
        "comments": 5,
        "hn_url": "https://news.ycombinator.com/item?id=34049848",
        "item_id": 34049848,
        "ratio": 0.16129032258064516,
        "score": 31,
        "submission_time": "2022-12-19T08:38:51",
        "title": "With food available, many bears at Tahoe forgo hibernation",
        "url": "https://www.tahoedailytribune.com/news/with-food-available-many-bears-at-tahoe-forgo-hibernation/"
    },
    {
        "blocks": 7,
        "by": "kevmo314",
        "comments": 41,
        "hn_url": "https://news.ycombinator.com/item?id=34055101",
        "item_id": 34055101,
        "ratio": 0.14487632508833923,
        "score": 283,
        "submission_time": "2022-12-19T17:50:34",
        "title": "Video codec in 100 lines of Rust",
        "url": "https://blog.tempus-ex.com/hello-video-codec/"
    },
    {
        "blocks": 2,
        "by": "gizzlon",
        "comments": 1,
        "hn_url": "https://news.ycombinator.com/item?id=34063247",
        "item_id": 34063247,
        "ratio": 0.05,
        "score": 20,
        "submission_time": "2022-12-20T08:41:19",
        "title": "With Binance, Everything Is Not Fine",
        "url": "https://www.coindesk.com/consensus-magazine/2022/12/19/cz-binance-crypto-exchange-red-flags-cnbc-ftx/"
    }
]